joule/__init__.py
joule/app_keys.py
joule/cli.py
joule/constants.py
joule/daemon.py
joule/errors.py
joule/middleware.py
joule/migrations.py
joule/update_users.py
joule/version.py
joule/api/__init__.py
joule/api/annotation.py
joule/api/data.py
joule/api/data_stream.py
joule/api/db.py
joule/api/event.py
joule/api/event_stream.py
joule/api/folder.py
joule/api/folder_type.py
joule/api/follower.py
joule/api/helpers.py
joule/api/master.py
joule/api/module.py
joule/api/proxy.py
joule/api/node/__init__.py
joule/api/node/base_node.py
joule/api/node/node_config.py
joule/api/node/node_info.py
joule/api/node/tcp_node.py
joule/api/node/unix_node.py
joule/api/session/__init__.py
joule/api/session/base_session.py
joule/api/session/tcp_session.py
joule/api/session/unix_session.py
joule/cli/__init__.py
joule/cli/__main__.py
joule/cli/config.py
joule/cli/folder.py
joule/cli/lazy_group.py
joule/cli/admin/__init__.py
joule/cli/admin/authorize.py
joule/cli/admin/erase.py
joule/cli/admin/initialize.py
joule/cli/admin/local_postgres_templates/pg_hba.conf.jinja2
joule/cli/admin/local_postgres_templates/pg_ident.conf.jinja2
joule/cli/admin/local_postgres_templates/postgresql.conf.jinja2
joule/cli/admin/local_postgres_templates/recovery.conf.jinja2
joule/cli/data/__init__.py
joule/cli/data/consolidate.py
joule/cli/data/copy.py
joule/cli/data/delete.py
joule/cli/data/ingest.py
joule/cli/data/intervals.py
joule/cli/data/mean.py
joule/cli/data/median.py
joule/cli/data/merge.py
joule/cli/data/read.py
joule/cli/event/__init__.py
joule/cli/event/copy.py
joule/cli/event/info.py
joule/cli/event/move.py
joule/cli/event/rename.py
joule/cli/follower/__init__.py
joule/cli/follower/delete.py
joule/cli/follower/list.py
joule/cli/master/__init__.py
joule/cli/master/add.py
joule/cli/master/delete.py
joule/cli/master/list.py
joule/cli/module/__init__.py
joule/cli/module/info.py
joule/cli/module/list.py
joule/cli/module/logs.py
joule/cli/node/__init__.py
joule/cli/node/add.py
joule/cli/node/default.py
joule-0.12.1.dist-info/licenses/LICENSE
joule-0.12.1.dist-info/METADATA
joule-0.12.1.dist-info/WHEEL
joule-0.12.1.dist-info/entry_points.txt
joule-0.12.1.dist-info/top_level.txt
joule-0.12.1.dist-info/RECORD
