Metadata-Version: 2.4
Name: joule
Version: 0.12.1
Summary: Decentralized data processing for IoT platforms
Author-email: John Donnal <donnal@usna.edu>
License-Expression: LicenseRef-Custom-License
Project-URL: Homepage, https://wattsworth.net/joule/
Project-URL: Bug Tracker, https://github.com/wattsworth/joule/issues
Classifier: Programming Language :: Python :: 3
Classifier: Operating System :: POSIX :: Linux
Classifier: Operating System :: Microsoft :: Windows
Classifier: Operating System :: MacOS :: MacOS X
Requires-Python: >=3.9
License-File: LICENSE
Requires-Dist: click
Requires-Dist: treelib
Requires-Dist: numpy
Requires-Dist: scipy
Requires-Dist: psutil
Requires-Dist: aiohttp<4,>=3
Requires-Dist: markdown
Requires-Dist: BeautifulSoup4
Requires-Dist: dateparser
Requires-Dist: tabulate
Requires-Dist: sqlalchemy
Requires-Dist: sqlalchemy-utils
Requires-Dist: aiohttp-jinja2
Requires-Dist: jinja2
Requires-Dist: asyncpg
Requires-Dist: psycopg2-binary
Requires-Dist: aiodns
Requires-Dist: pyopenssl
Requires-Dist: dsnparse
Requires-Dist: h5py
Requires-Dist: requests
Requires-Dist: packaging
Provides-Extra: tests
Requires-Dist: testing.postgresql; extra == "tests"
Requires-Dist: requests; extra == "tests"
Requires-Dist: icecream; extra == "tests"
Dynamic: license-file
